labManager/master.py
labManager/GUI/master/__init__.py
labManager/GUI/master/_impl/computer_list.py
labManager/GUI/master/_impl/file_commander.py
labManager/GUI/master/_impl/filepicker.py
labManager/GUI/master/_impl/msgbox.py
labManager/GUI/master/_impl/utils.py
labmanager_master-1.0.5.dist-info/METADATA
labmanager_master-1.0.5.dist-info/WHEEL
labmanager_master-1.0.5.dist-info/licenses/LICENSE
labmanager_master-1.0.5.dist-info/RECORD
